odoo/addons/mgmtsystem_nonconformity_mrp/README.rst
odoo/addons/mgmtsystem_nonconformity_mrp/__init__.py
odoo/addons/mgmtsystem_nonconformity_mrp/__manifest__.py
odoo/addons/mgmtsystem_nonconformity_mrp/i18n/it.po
odoo/addons/mgmtsystem_nonconformity_mrp/i18n/mgmtsystem_extended_mrp.pot
odoo/addons/mgmtsystem_nonconformity_mrp/i18n/mgmtsystem_nonconformity_mrp.pot
odoo/addons/mgmtsystem_nonconformity_mrp/models/__init__.py
odoo/addons/mgmtsystem_nonconformity_mrp/models/mgmtsystem_nonconformity_mrp.py
odoo/addons/mgmtsystem_nonconformity_mrp/readme/CONFIGURE.rst
odoo/addons/mgmtsystem_nonconformity_mrp/readme/CONTRIBUTORS.rst
odoo/addons/mgmtsystem_nonconformity_mrp/readme/DESCRIPTION.rst
odoo/addons/mgmtsystem_nonconformity_mrp/readme/HISTORY.rst
odoo/addons/mgmtsystem_nonconformity_mrp/readme/INSTALL.rst
odoo/addons/mgmtsystem_nonconformity_mrp/readme/USAGE.rst
odoo/addons/mgmtsystem_nonconformity_mrp/static/description/icon.png
odoo/addons/mgmtsystem_nonconformity_mrp/static/description/index.html
odoo/addons/mgmtsystem_nonconformity_mrp/views/mgmtsystem_nonconformity_views.xml
odoo13_addon_mgmtsystem_nonconformity_mrp-13.0.1.0.1.dev10.dist-info/METADATA
odoo13_addon_mgmtsystem_nonconformity_mrp-13.0.1.0.1.dev10.dist-info/WHEEL
odoo13_addon_mgmtsystem_nonconformity_mrp-13.0.1.0.1.dev10.dist-info/top_level.txt
odoo13_addon_mgmtsystem_nonconformity_mrp-13.0.1.0.1.dev10.dist-info/RECORD
